pygame_ui_utilities-0.1.0.dist-info/licenses/LICENSE
pygame_utilities/__init__.py
pygame_utilities/ui/__init__.py
pygame_utilities/ui/text_drawing.py
pygame_utilities/ui/ui_buttons.py
pygame_ui_utilities-0.1.0.dist-info/METADATA
pygame_ui_utilities-0.1.0.dist-info/WHEEL
pygame_ui_utilities-0.1.0.dist-info/top_level.txt
pygame_ui_utilities-0.1.0.dist-info/RECORD
